Metadata-Version: 2.1
Name: relazioni
Version: 0.0.2
Summary: A lightweight package for strength of the relationship between two variables analysis.
Home-page: https://github.com/chicodelarosa/relazioni
Author: Dan A. Rosa De Jesús
Author-email: contact@chicodelarosa.com
License: UNKNOWN
Project-URL: Bug Tracker, https://github.com/chicodelarosa/relazioni/issues
Platform: UNKNOWN
Classifier: Programming Language :: Python :: 3
Classifier: License :: OSI Approved :: MIT License
Classifier: Operating System :: OS Independent
Requires-Python: >=3.6
License-File: LICENSE
